{
  "head": {
    "signInfo": "",
    "receiptType": 0,
    "bizCode": "DUB00113",
    "appId": "ALIYUN01",
    "bizId": "E67f5c0993a86361e72333106",
    "resultCode": "0",
    "msgId": "35819305",
    "resultMessage": "识别成功",
    "version": "1.0",
    "timestampStr": "2026-03-06 15:46:27",
    "receiveId": "EBAO0001"
  },
  "content": {
    "preDecHead": [
      {
        "processBitMap": "0",
        "sourceList": [
          {
            "attType": "Declaration",
            "imageId": 3,
            "transformValue": "杭州盛威实业有限公司",
            "originalValue": "杭州盛威实业有限公司",
            "normalizedValue": "杭州盛威实业有限公司",
            "processBitMap": "0",
            "axisX": 284,
            "sepValue": "杭州盛威实业有限公司",
            "axisY": 260,
            "width": 288,
            "attTypeCode": 4,
            "height": 33
          },
          {
            "attType": "Contract",
            "imageId": 4,
            "transformValue": "杭州盛威实业有限公司",
            "originalValue": "杭州盛威实业有限公司",
            "normalizedValue": "杭州盛威实业有限公司",
            "processBitMap": "0",
            "axisX": 561,
            "sepValue": "杭州盛威实业有限公司",
            "axisY": 91,
            "width": 436,
            "attTypeCode": 1,
            "height": 48
          },
          {
            "attType": "Invoice",
            "imageId": 1,
            "transformValue": "HANGZHOUSUNWAYINDUSTRYCO.,LTD",
            "originalValue": "HANGZHOUSUNWAYINDUSTRYCO.,LTD",
            "normalizedValue": "HANGZHOUSUNWAYINDUSTRYCO.,LTD",
            "processBitMap": "0",
            "axisX": 85,
            "sepValue": "HANGZHOUSUNWAYINDUSTRYCO.,LTD",
            "axisY": 156,
            "width": 866,
            "attTypeCode": 2,
            "height": 246
          },
          {
            "attType": "PackingList",
            "imageId": 2,
            "transformValue": "HANGZHOUSUNWAYINDUSTRYCO.,LTD.",
            "originalValue": "HANGZHOUSUNWAYINDUSTRYCO.,LTD.",
            "normalizedValue": "HANGZHOUSUNWAYINDUSTRYCO.,LTD.",
            "processBitMap": "0",
            "axisX": 46,
            "sepValue": "HANGZHOUSUNWAYINDUSTRYCO.,LTD.",
            "axisY": 192,
            "width": 570,
            "attTypeCode": 3,
            "height": 30
          }
        ],
        "source_image": 3,
        "originalValue": "杭州盛威实业有限公司",
        "normalizedValue": "杭州盛威实业有限公司",
        "keyDesc": "境内收发货人名称",
        "value": "杭州盛威实业有限公司",
        "key": "consigneeCname"
      },
      {
        "processBitMap": "0",
        "sourceList": [
          {
            "attType": "Declaration",
            "imageId": 3,
            "transformValue": "LNL INDUSTRIES KATARZYNA PAWLICKA SPÓLKA KOMANDYTOWA",
            "originalValue": "LNL INDUSTRIES KATARZYNA PAWLICKA SPÓLKA KOMANDYTOWA",
            "normalizedValue": "LNL INDUSTRIES KATARZYNA PAWLICKA SPÓLKA KOMANDYTOWA",
            "processBitMap": "0",
            "axisX": 284,
            "sepValue": "LNL INDUSTRIES KATARZYNA PAWLICKA SPÓLKA KOMANDYTOWA",
            "axisY": 300,
            "width": 972,
            "attTypeCode": 4,
            "height": 33
          },
          {
            "attType": "Contract",
            "imageId": 4,
            "transformValue": "LNL INDUSTRIES KATARZYNA PAWLICKA SPÓLKA KOMANDYTOWA",
            "originalValue": "LNL INDUSTRIES KATARZYNA PAWLICKA SPÓŁKA KOMANDYTOWA",
            "normalizedValue": "LNL INDUSTRIES KATARZYNA PAWLICKA SPÓŁKA KOMANDYTOWA",
            "processBitMap": "0",
            "axisX": 244,
            "sepValue": "LNL INDUSTRIES KATARZYNA PAWLICKA SPÓŁKA KOMANDYTOWA",
            "axisY": 369,
            "width": 710,
            "attTypeCode": 1,
            "height": 25
          },
          {
            "attType": "Invoice",
            "imageId": 1,
            "transformValue": "LNL INDUSTRIES KATARZYNA PAWLICKA SPÓLKA KOMANDYTOWA",
            "originalValue": "LNL INDUSTRIES KATARZYNA PAWLICKA SPÓŁKA KOMANDYTOWA",
            "normalizedValue": "LNL INDUSTRIES KATARZYNA PAWLICKA SPÓŁKA KOMANDYTOWA",
            "processBitMap": "0",
            "axisX": 85,
            "sepValue": "LNL INDUSTRIES KATARZYNA PAWLICKA SPÓŁKA KOMANDYTOWA",
            "axisY": 422,
            "width": 866,
            "attTypeCode": 2,
            "height": 293
          },
          {
            "attType": "PackingList",
            "imageId": 2,
            "transformValue": "LNL INDUSTRIES KATARZYNA PAWLICKA SPÓLKA KOMANDYTOWA",
            "originalValue": "LNL INDUSTRIES KATARZYNA PAWLICKA SPÓŁKA KOMANDYTOWA",
            "normalizedValue": "LNL INDUSTRIES KATARZYNA PAWLICKA SPÓŁKA KOMANDYTOWA",
            "processBitMap": "0",
            "axisX": 46,
            "sepValue": "LNL INDUSTRIES KATARZYNA PAWLICKA SPÓŁKA KOMANDYTOWA",
            "axisY": 450,
            "width": 686,
            "attTypeCode": 3,
            "height": 25
          }
        ],
        "source_image": 3,
        "originalValue": "LNL INDUSTRIES KATARZYNA PAWLICKA SPÓLKA KOMANDYTOWA",
        "normalizedValue": "LNL INDUSTRIES KATARZYNA PAWLICKA SPÓLKA KOMANDYTOWA",
        "keyDesc": "境外收发货人",
        "value": "LNL INDUSTRIES KATARZYNA PAWLICKA SPÓLKA KOMANDYTOWA",
        "key": "consignorEname"
      },
      {
        "processBitMap": "0",
        "sourceList": [
          {
            "attType": "Declaration",
            "imageId": 3,
            "transformValue": "POL",
            "originalValue": "波兰",
            "normalizedValue": "波兰",
            "processBitMap": "0",
            "axisX": 874,
            "sepValue": "波兰",
            "axisY": 543,
            "width": 62,
            "attTypeCode": 4,
            "height": 33
          },
          {
            "attType": "Contract",
            "imageId": 4,
            "transformValue": "POL",
            "originalValue": "POLAND",
            "normalizedValue": "POLAND",
            "processBitMap": "0",
            "axisX": 763,
            "sepValue": "POLAND",
            "axisY": 1001,
            "width": 129,
            "attTypeCode": 1,
            "height": 25
          },
          {
            "attType": "Invoice",
            "imageId": 1,
            "transformValue": "POL",
            "originalValue": "POLAND",
            "normalizedValue": "POLAND",
            "processBitMap": "0",
            "axisX": 85,
            "sepValue": "POLAND",
            "axisY": 816,
            "width": 866,
            "attTypeCode": 2,
            "height": 76
          },
          {
            "attType": "PackingList",
            "imageId": 2,
            "transformValue": "POL",
            "originalValue": "POLAND",
            "normalizedValue": "POLAND",
            "processBitMap": "0",
            "axisX": 500,
            "sepValue": "POLAND",
            "axisY": 829,
            "width": 125,
            "attTypeCode": 3,
            "height": 30
          }
        ],
        "source_image": 3,
        "originalValue": "波兰",
        "normalizedValue": "POL",
        "keyDesc": "运抵国",
        "value": "POL",
        "key": "cusTradeCountry"
      },
      {
        "processBitMap": "0",
        "sourceList": [
          {
            "attType": "Declaration",
            "imageId": 3,
            "transformValue": "3",
            "originalValue": "FOB",
            "normalizedValue": "FOB",
            "processBitMap": "0",
            "axisX": 1458,
            "sepValue": "FOB",
            "axisY": 710,
            "width": 58,
            "attTypeCode": 4,
            "height": 33
          },
          {
            "attType": "Contract",
            "imageId": 4,
            "transformValue": "3",
            "originalValue": "FOB",
            "normalizedValue": "FOB",
            "processBitMap": "0",
            "axisX": 371,
            "sepValue": "FOB",
            "axisY": 1051,
            "width": 56,
            "attTypeCode": 1,
            "height": 26
          },
          {
            "attType": "Invoice",
            "imageId": 1,
            "transformValue": "3",
            "originalValue": "FOB",
            "normalizedValue": "FOB",
            "processBitMap": "0",
            "axisX": 960,
            "sepValue": "FOB",
            "axisY": 816,
            "width": 616,
            "attTypeCode": 2,
            "height": 76
          }
        ],
        "source_image": 3,
        "originalValue": "FOB",
        "normalizedValue": "3",
        "keyDesc": "成交方式",
        "value": "3",
        "key": "transMode"
      },
      {
        "processBitMap": "0",
        "sourceList": [
          {
            "attType": "Invoice",
            "imageId": 1,
            "transformValue": "183500",
            "originalValue": "183500",
            "normalizedValue": "183500",
            "processBitMap": "0",
            "axisX": 1310,
            "sepValue": "183500",
            "axisY": 1812,
            "width": 177,
            "attTypeCode": 2,
            "height": 38
          },
          {
            "attType": "Contract",
            "imageId": 4,
            "transformValue": "183500",
            "originalValue": "183500",
            "normalizedValue": "183500",
            "processBitMap": "0",
            "axisX": 1262,
            "sepValue": "183500",
            "axisY": 847,
            "width": 173,
            "attTypeCode": 1,
            "height": 32
          }
        ],
        "source_image": 1,
        "originalValue": "183500",
        "normalizedValue": "183500",
        "keyDesc": "总价总和",
        "value": "183500",
        "key": "totalAmount"
      },
      {
        "processBitMap": "0",
        "sourceList": [
          {
            "attType": "Declaration",
            "imageId": 3,
            "transformValue": "杭州盛威实业有限公司",
            "originalValue": "杭州盛威实业有限公司",
            "normalizedValue": "杭州盛威实业有限公司",
            "processBitMap": "0",
            "axisX": 284,
            "sepValue": "杭州盛威实业有限公司",
            "axisY": 341,
            "width": 288,
            "attTypeCode": 4,
            "height": 33
          },
          {
            "attType": "Invoice",
            "imageId": 1,
            "transformValue": "杭州盛威实业有限公司",
            "originalValue": "杭州盛威实业有限公司",
            "normalizedValue": "杭州盛威实业有限公司",
            "processBitMap": "0",
            "axisX": 1006,
            "sepValue": "杭州盛威实业有限公司",
            "axisY": 197,
            "width": 520,
            "attTypeCode": 2,
            "height": 126
          }
        ],
        "source_image": 3,
        "originalValue": "杭州盛威实业有限公司",
        "normalizedValue": "杭州盛威实业有限公司",
        "keyDesc": "生产销售单位名称",
        "value": "杭州盛威实业有限公司",
        "key": "ownerName"
      },
      {
        "processBitMap": "0",
        "sourceList": [
          {
            "attType": "Declaration",
            "imageId": 3,
            "transformValue": "POL009",
            "originalValue": "GDYNIA, POLAND",
            "normalizedValue": "GDYNIA, POLAND",
            "processBitMap": "0",
            "axisX": 1192,
            "sepValue": "GDYNIA, POLAND",
            "axisY": 543,
            "width": 198,
            "attTypeCode": 4,
            "height": 33
          },
          {
            "attType": "Contract",
            "imageId": 4,
            "transformValue": "POL009",
            "originalValue": "GDYNIA",
            "normalizedValue": "GDYNIA",
            "processBitMap": "0",
            "axisX": 665,
            "sepValue": "GDYNIA",
            "axisY": 1001,
            "width": 89,
            "attTypeCode": 1,
            "height": 25
          },
          {
            "attType": "PackingList",
            "imageId": 2,
            "transformValue": "POL009",
            "originalValue": "GDYNIA",
            "normalizedValue": "GDYNIA",
            "processBitMap": "0",
            "axisX": 366,
            "sepValue": "GDYNIA",
            "axisY": 829,
            "width": 125,
            "attTypeCode": 3,
            "height": 30
          }
        ],
        "source_image": 3,
        "originalValue": "GDYNIA, POLAND",
        "normalizedValue": "POL009",
        "keyDesc": "指运港",
        "value": "POL009",
        "key": "distinatePort"
      },
      {
        "processBitMap": "0",
        "sourceList": [
          {
            "attType": "Declaration",
            "imageId": 3,
            "transformValue": "2166",
            "originalValue": "2166",
            "normalizedValue": "2166",
            "processBitMap": "0",
            "axisX": 468,
            "sepValue": "2166",
            "axisY": 710,
            "width": 62,
            "attTypeCode": 4,
            "height": 33
          },
          {
            "attType": "PackingList",
            "imageId": 2,
            "transformValue": "2166",
            "originalValue": "2166",
            "normalizedValue": "2166",
            "processBitMap": "0",
            "axisX": 679,
            "sepValue": "2166",
            "axisY": 1769,
            "width": 71,
            "attTypeCode": 3,
            "height": 26
          }
        ],
        "source_image": 3,
        "originalValue": "2166",
        "normalizedValue": "2166",
        "keyDesc": "件数",
        "value": "2166",
        "key": "packNo"
      },
      {
        "processBitMap": "0",
        "sourceList": [
          {
            "attType": "Declaration",
            "imageId": 3,
            "transformValue": "纸箱",
            "originalValue": "纸箱",
            "normalizedValue": "纸箱",
            "processBitMap": "0",
            "axisX": 323,
            "sepValue": "纸箱",
            "axisY": 710,
            "width": 63,
            "attTypeCode": 4,
            "height": 33
          },
          {
            "attType": "PackingList",
            "imageId": 2,
            "transformValue": "CTNS",
            "originalValue": "CTNS",
            "normalizedValue": "CTNS",
            "processBitMap": "0",
            "axisX": 759,
            "sepValue": "CTNS",
            "axisY": 1769,
            "width": 63,
            "attTypeCode": 3,
            "height": 26
          }
        ],
        "source_image": 3,
        "originalValue": "纸箱",
        "normalizedValue": "22",
        "keyDesc": "包装种类",
        "value": "22",
        "key": "wrapType"
      },
      {
        "processBitMap": "0",
        "sourceList": [
          {
            "attType": "Declaration",
            "imageId": 3,
            "transformValue": "20700",
            "originalValue": "20700",
            "normalizedValue": "20700",
            "processBitMap": "0",
            "axisX": 736,
            "sepValue": "20700",
            "axisY": 710,
            "width": 113,
            "attTypeCode": 4,
            "height": 33
          },
          {
            "attType": "PackingList",
            "imageId": 2,
            "transformValue": "20700",
            "originalValue": "20700",
            "normalizedValue": "20700",
            "processBitMap": "0",
            "axisX": 1027,
            "sepValue": "20700",
            "axisY": 1769,
            "width": 144,
            "attTypeCode": 3,
            "height": 26
          }
        ],
        "source_image": 3,
        "originalValue": "20700",
        "normalizedValue": "20700",
        "keyDesc": "毛重",
        "value": "20700",
        "key": "grossWt"
      },
      {
        "processBitMap": "0",
        "sourceList": [
          {
            "attType": "Declaration",
            "imageId": 3,
            "transformValue": "18630",
            "originalValue": "18630",
            "normalizedValue": "18630",
            "processBitMap": "0",
            "axisX": 1045,
            "sepValue": "18630",
            "axisY": 710,
            "width": 113,
            "attTypeCode": 4,
            "height": 33
          },
          {
            "attType": "PackingList",
            "imageId": 2,
            "transformValue": "18630",
            "originalValue": "18630",
            "normalizedValue": "18630",
            "processBitMap": "0",
            "axisX": 1260,
            "sepValue": "18630",
            "axisY": 1769,
            "width": 134,
            "attTypeCode": 3,
            "height": 26
          }
        ],
        "source_image": 3,
        "originalValue": "18630",
        "normalizedValue": "18630",
        "keyDesc": "净重",
        "value": "18630",
        "key": "netWt"
      },
      {
        "processBitMap": "0",
        "sourceList": [
          {
            "attType": "Declaration",
            "imageId": 3,
            "transformValue": "3316963008",
            "originalValue": "3316963008",
            "normalizedValue": "3316963008",
            "processBitMap": "0",
            "axisX": 572,
            "sepValue": "3316963008",
            "axisY": 260,
            "width": 160,
            "attTypeCode": 4,
            "height": 33
          }
        ],
        "source_image": 3,
        "originalValue": "3316963008",
        "normalizedValue": "3316963008",
        "keyDesc": "境内收发货人海关代码",
        "value": "3316963008",
        "key": "rcvgdTradeCode"
      },
      {
        "processBitMap": "0",
        "sourceList": [
          {
            "attType": "Declaration",
            "imageId": 3,
            "transformValue": "9133010972587504XT",
            "originalValue": "9133010972587504XT",
            "normalizedValue": "9133010972587504XT",
            "processBitMap": "0",
            "axisX": 741,
            "sepValue": "9133010972587504XT",
            "axisY": 260,
            "width": 274,
            "attTypeCode": 4,
            "height": 33
          }
        ],
        "source_image": 3,
        "originalValue": "9133010972587504XT",
        "normalizedValue": "9133010972587504XT",
        "keyDesc": "境内收发货人社会信用代码",
        "value": "9133010972587504XT",
        "key": "rcvgdTradeScc"
      },
      {
        "processBitMap": "0",
        "sourceList": [
          {
            "attType": "Declaration",
            "imageId": 3,
            "transformValue": "3316963008",
            "originalValue": "3316963008",
            "normalizedValue": "3316963008",
            "processBitMap": "0",
            "axisX": 572,
            "sepValue": "3316963008",
            "axisY": 341,
            "width": 160,
            "attTypeCode": 4,
            "height": 33
          }
        ],
        "source_image": 3,
        "originalValue": "3316963008",
        "normalizedValue": "3316963008",
        "keyDesc": "生产销售单位海关代码",
        "value": "3316963008",
        "key": "ownerCode"
      },
      {
        "processBitMap": "0",
        "sourceList": [
          {
            "attType": "Declaration",
            "imageId": 3,
            "transformValue": "9133010972587504XT",
            "originalValue": "9133010972587504XT",
            "normalizedValue": "9133010972587504XT",
            "processBitMap": "0",
            "axisX": 741,
            "sepValue": "9133010972587504XT",
            "axisY": 341,
            "width": 274,
            "attTypeCode": 4,
            "height": 33
          }
        ],
        "source_image": 3,
        "originalValue": "9133010972587504XT",
        "normalizedValue": "9133010972587504XT",
        "keyDesc": "生产销售单位社会信用代码",
        "value": "9133010972587504XT",
        "key": "ownerScc"
      },
      {
        "processBitMap": "0",
        "sourceList": [
          {
            "attType": "Declaration",
            "imageId": 3,
            "transformValue": "0110",
            "originalValue": "一般贸易",
            "normalizedValue": "一般贸易",
            "processBitMap": "0",
            "axisX": 727,
            "sepValue": "一般贸易",
            "axisY": 402,
            "width": 122,
            "attTypeCode": 4,
            "height": 32
          }
        ],
        "source_image": 3,
        "originalValue": "一般贸易",
        "normalizedValue": "0110",
        "keyDesc": "监管方式",
        "value": "0110",
        "key": "supvModeCode"
      },
      {
        "processBitMap": "0",
        "sourceList": [
          {
            "attType": "Declaration",
            "imageId": 3,
            "transformValue": "HLCUNG12503DTJV3",
            "originalValue": "HLCUNG12503DTJV3",
            "normalizedValue": "HLCUNG12503DTJV3",
            "processBitMap": "0",
            "axisX": 1192,
            "sepValue": "HLCUNG12503DTJV3",
            "axisY": 402,
            "width": 291,
            "attTypeCode": 4,
            "height": 32
          }
        ],
        "source_image": 3,
        "originalValue": "HLCUNG12503DTJV3",
        "normalizedValue": "HLCUNG12503DTJV3",
        "keyDesc": "提运单号",
        "value": "HLCUNG12503DTJV3",
        "key": "billNo"
      },
      {
        "processBitMap": "0",
        "sourceList": [
          {
            "attType": "Declaration",
            "imageId": 3,
            "transformValue": "SW241205SA3B",
            "originalValue": "SW241205SA3B",
            "normalizedValue": "SW241205SA3B",
            "processBitMap": "0",
            "axisX": 284,
            "sepValue": "SW241205SA3B",
            "axisY": 543,
            "width": 207,
            "attTypeCode": 4,
            "height": 33
          },
          {
            "attType": "Contract",
            "imageId": 4,
            "transformValue": "SW241205SA3B",
            "originalValue": "SW241205SA3B",
            "normalizedValue": "SW241205SA3B",
            "processBitMap": "0",
            "axisX": 1210,
            "sepValue": "SW241205SA3B",
            "axisY": 290,
            "width": 168,
            "attTypeCode": 1,
            "height": 31
          }
        ],
        "source_image": 3,
        "originalValue": "SW241205SA3B",
        "normalizedValue": "SW241205SA3B",
        "keyDesc": "合同协议号",
        "value": "SW241205SA3B",
        "key": "contrNo"
      },
      {
        "processBitMap": "0",
        "sourceList": [
          {
            "attType": "Declaration",
            "imageId": 3,
            "transformValue": "POL",
            "originalValue": "波兰",
            "normalizedValue": "波兰",
            "processBitMap": "0",
            "axisX": 575,
            "sepValue": "波兰",
            "axisY": 543,
            "width": 63,
            "attTypeCode": 4,
            "height": 33
          }
        ],
        "source_image": 3,
        "originalValue": "波兰",
        "normalizedValue": "POL",
        "keyDesc": "贸易国",
        "value": "POL",
        "key": "cusTradeNationCode"
      },
      {
        "processBitMap": "0",
        "sourceList": [
          {
            "attType": "Declaration",
            "imageId": 3,
            "transformValue": "宁波",
            "originalValue": "宁波",
            "normalizedValue": "宁波",
            "processBitMap": "0",
            "axisX": 1458,
            "sepValue": "宁波",
            "axisY": 543,
            "width": 61,
            "attTypeCode": 4,
            "height": 33
          }
        ],
        "source_image": 3,
        "originalValue": "宁波",
        "normalizedValue": "宁波",
        "keyDesc": "出境关别",
        "value": "宁波",
        "key": "iEPort"
      }
    ],
    "preDecList": [
      [
        {
          "processBitMap": "0",
          "sourceList": [
            {
              "attType": "Declaration",
              "imageId": 3,
              "transformValue": "淋浴房",
              "originalValue": "淋浴房",
              "normalizedValue": "淋浴房",
              "processBitMap": "0",
              "axisX": 284,
              "sepValue": "淋浴房",
              "axisY": 1024,
              "width": 91,
              "attTypeCode": 4,
              "height": 32
            },
            {
              "attType": "Contract",
              "imageId": 4,
              "transformValue": "淋浴房",
              "originalValue": "SHOWER ENCLOSURE",
              "normalizedValue": "SHOWER ENCLOSURE",
              "processBitMap": "0",
              "axisX": 423,
              "sepValue": "SHOWER ENCLOSURE",
              "axisY": 799,
              "width": 181,
              "attTypeCode": 1,
              "height": 25
            },
            {
              "attType": "Invoice",
              "imageId": 1,
              "transformValue": "淋浴房",
              "originalValue": "SHOWER ENCLOSURE",
              "normalizedValue": "SHOWER ENCLOSURE",
              "processBitMap": "0",
              "axisX": 85,
              "sepValue": "SHOWER ENCLOSURE",
              "axisY": 1158,
              "width": 254,
              "attTypeCode": 2,
              "height": 30
            },
            {
              "attType": "PackingList",
              "imageId": 2,
              "transformValue": "淋浴房",
              "originalValue": "SHOWER ENCLOSURE",
              "normalizedValue": "SHOWER ENCLOSURE",
              "processBitMap": "0",
              "axisX": 46,
              "sepValue": "SHOWER ENCLOSURE",
              "axisY": 1125,
              "width": 222,
              "attTypeCode": 3,
              "height": 25
            }
          ],
          "source_image": 3,
          "originalValue": "淋浴房",
          "normalizedValue": "淋浴房",
          "keyDesc": "商品名称",
          "value": "淋浴房",
          "key": "gName"
        },
        {
          "processBitMap": "0",
          "sourceList": [
            {
              "attType": "Invoice",
              "imageId": 1,
              "transformValue": "18630",
              "originalValue": "18630",
              "normalizedValue": "18630",
              "processBitMap": "0",
              "axisX": 983,
              "sepValue": "18630",
              "axisY": 1158,
              "width": 173,
              "attTypeCode": 2,
              "height": 30
            },
            {
              "attType": "PackingList",
              "imageId": 2,
              "transformValue": "2166",
              "originalValue": "2166",
              "normalizedValue": "2166",
              "processBitMap": "0",
              "axisX": 670,
              "sepValue": "2166",
              "axisY": 1125,
              "width": 71,
              "attTypeCode": 3,
              "height": 25
            },
            {
              "attType": "Contract",
              "imageId": 4,
              "transformValue": "18630",
              "originalValue": "18630",
              "normalizedValue": "18630",
              "processBitMap": "0",
              "axisX": 800,
              "sepValue": "18630",
              "axisY": 791,
              "width": 120,
              "attTypeCode": 1,
              "height": 30
            }
          ],
          "source_image": 1,
          "originalValue": "18630",
          "normalizedValue": "18630",
          "keyDesc": "成交数量",
          "value": "18630",
          "key": "gQty"
        },
        {
          "processBitMap": "0",
          "sourceList": [
            {
              "attType": "Invoice",
              "imageId": 1,
              "transformValue": "KGS",
              "originalValue": "KGS",
              "normalizedValue": "KGS",
              "processBitMap": "0",
              "axisX": 983,
              "sepValue": "KGS",
              "axisY": 1158,
              "width": 173,
              "attTypeCode": 2,
              "height": 30
            },
            {
              "attType": "PackingList",
              "imageId": 2,
              "transformValue": "CTNS",
              "originalValue": "CTNS",
              "normalizedValue": "CTNS",
              "processBitMap": "0",
              "axisX": 750,
              "sepValue": "CTNS",
              "axisY": 1125,
              "width": 72,
              "attTypeCode": 3,
              "height": 25
            },
            {
              "attType": "Contract",
              "imageId": 4,
              "transformValue": "KGS",
              "originalValue": "KGS",
              "normalizedValue": "KGS",
              "processBitMap": "0",
              "axisX": 922,
              "sepValue": "KGS",
              "axisY": 791,
              "width": 64,
              "attTypeCode": 1,
              "height": 30
            }
          ],
          "source_image": 1,
          "originalValue": "KGS",
          "normalizedValue": "KGS",
          "keyDesc": "成交单位",
          "value": "KGS",
          "key": "gUnit"
        },
        {
          "processBitMap": "0",
          "sourceList": [
            {
              "attType": "Declaration",
              "imageId": 3,
              "transformValue": "9.85",
              "originalValue": "9.85",
              "normalizedValue": "9.85",
              "processBitMap": "0",
              "axisX": 1063,
              "sepValue": "9.85",
              "axisY": 1024,
              "width": 84,
              "attTypeCode": 4,
              "height": 32
            },
            {
              "attType": "Invoice",
              "imageId": 1,
              "transformValue": "9.85",
              "originalValue": "9.85",
              "normalizedValue": "9.85",
              "processBitMap": "0",
              "axisX": 1262,
              "sepValue": "9.85",
              "axisY": 1158,
              "width": 78,
              "attTypeCode": 2,
              "height": 30
            },
            {
              "attType": "Contract",
              "imageId": 4,
              "transformValue": "9.85",
              "originalValue": "9.85",
              "normalizedValue": "9.85",
              "processBitMap": "0",
              "axisX": 1058,
              "sepValue": "9.85",
              "axisY": 793,
              "width": 91,
              "attTypeCode": 1,
              "height": 31
            }
          ],
          "source_image": 3,
          "originalValue": "9.85",
          "normalizedValue": "9.85",
          "keyDesc": "单价",
          "value": "9.85",
          "key": "declPrice"
        },
        {
          "processBitMap": "0",
          "sourceList": [
            {
              "attType": "Declaration",
              "imageId": 3,
              "transformValue": "183500",
              "originalValue": "183500",
              "normalizedValue": "183500",
              "processBitMap": "0",
              "axisX": 1197,
              "sepValue": "183500",
              "axisY": 1024,
              "width": 165,
              "attTypeCode": 4,
              "height": 32
            },
            {
              "attType": "Invoice",
              "imageId": 1,
              "transformValue": "183500",
              "originalValue": "183500",
              "normalizedValue": "183500",
              "processBitMap": "0",
              "axisX": 1408,
              "sepValue": "183500",
              "axisY": 1158,
              "width": 161,
              "attTypeCode": 2,
              "height": 30
            },
            {
              "attType": "Contract",
              "imageId": 4,
              "transformValue": "183500",
              "originalValue": "183500",
              "normalizedValue": "183500",
              "processBitMap": "0",
              "axisX": 1272,
              "sepValue": "183500",
              "axisY": 793,
              "width": 163,
              "attTypeCode": 1,
              "height": 31
            }
          ],
          "source_image": 3,
          "originalValue": "183500",
          "normalizedValue": "183500",
          "keyDesc": "总价",
          "value": "183500",
          "key": "declTotal"
        },
        {
          "processBitMap": "0",
          "sourceList": [
            {
              "attType": "Declaration",
              "imageId": 3,
              "transformValue": "CNY",
              "originalValue": "人民币",
              "normalizedValue": "人民币",
              "processBitMap": "0",
              "axisX": 1564,
              "sepValue": "人民币",
              "axisY": 1024,
              "width": 89,
              "attTypeCode": 4,
              "height": 32
            },
            {
              "attType": "Contract",
              "imageId": 4,
              "transformValue": "CNY",
              "originalValue": "CNY",
              "normalizedValue": "CNY",
              "processBitMap": "0",
              "axisX": 1058,
              "sepValue": "CNY",
              "axisY": 793,
              "width": 23,
              "attTypeCode": 1,
              "height": 31
            },
            {
              "attType": "Invoice",
              "imageId": 1,
              "transformValue": "CNY",
              "originalValue": "CNY",
              "normalizedValue": "CNY",
              "processBitMap": "0",
              "axisX": 1408,
              "sepValue": "CNY",
              "axisY": 905,
              "width": 161,
              "attTypeCode": 2,
              "height": 76
            }
          ],
          "source_image": 3,
          "originalValue": "人民币",
          "normalizedValue": "CNY",
          "keyDesc": "币制",
          "value": "CNY",
          "key": "tradeCurr"
        },
        {
          "processBitMap": "0",
          "sourceList": [
            {
              "attType": "PackingList",
              "imageId": 2,
              "transformValue": "2166",
              "originalValue": "2166",
              "normalizedValue": "2166",
              "processBitMap": "0",
              "axisX": 670,
              "sepValue": "2166",
              "axisY": 1125,
              "width": 71,
              "attTypeCode": 3,
              "height": 25
            }
          ],
          "source_image": 2,
          "originalValue": "2166",
          "normalizedValue": "2166",
          "keyDesc": "件数单项",
          "value": "2166",
          "key": "gpackNo"
        },
        {
          "processBitMap": "0",
          "sourceList": [
            {
              "attType": "PackingList",
              "imageId": 2,
              "transformValue": "20700",
              "originalValue": "20700",
              "normalizedValue": "20700",
              "processBitMap": "0",
              "axisX": 992,
              "sepValue": "20700",
              "axisY": 1125,
              "width": 170,
              "attTypeCode": 3,
              "height": 25
            }
          ],
          "source_image": 2,
          "originalValue": "20700",
          "normalizedValue": "20700",
          "keyDesc": "毛重单项",
          "value": "20700",
          "key": "ggrossWt"
        },
        {
          "processBitMap": "0",
          "sourceList": [
            {
              "attType": "PackingList",
              "imageId": 2,
              "transformValue": "18630",
              "originalValue": "18630",
              "normalizedValue": "18630",
              "processBitMap": "0",
              "axisX": 1224,
              "sepValue": "18630",
              "axisY": 1125,
              "width": 170,
              "attTypeCode": 3,
              "height": 25
            },
            {
              "attType": "Declaration",
              "imageId": 3,
              "transformValue": "18630",
              "originalValue": "18630",
              "normalizedValue": "18630",
              "processBitMap": "0",
              "axisX": 749,
              "sepValue": "18630",
              "axisY": 1024,
              "width": 109,
              "attTypeCode": 4,
              "height": 32
            }
          ],
          "source_image": 2,
          "originalValue": "18630",
          "normalizedValue": "18630",
          "keyDesc": "净重单项",
          "value": "18630",
          "key": "gnetWt"
        },
        {
          "processBitMap": "0",
          "sourceList": [
            {
              "attType": "Declaration",
              "imageId": 3,
              "transformValue": "9406900090",
              "originalValue": "9406900090",
              "normalizedValue": "9406900090",
              "processBitMap": "0",
              "axisX": 126,
              "sepValue": "9406900090",
              "axisY": 1024,
              "width": 152,
              "attTypeCode": 4,
              "height": 32
            }
          ],
          "source_image": 3,
          "originalValue": "9406900090",
          "normalizedValue": "9406900090",
          "keyDesc": "商品编号",
          "value": "9406900090",
          "key": "codeTs"
        },
        {
          "processBitMap": "0",
          "sourceList": [
            {
              "attType": "Declaration",
              "imageId": 3,
              "transformValue": "500",
              "originalValue": "500",
              "normalizedValue": "500",
              "processBitMap": "0",
              "axisX": 284,
              "sepValue": "500",
              "axisY": 1107,
              "width": 46,
              "attTypeCode": 4,
              "height": 33
            }
          ],
          "source_image": 3,
          "originalValue": "500",
          "normalizedValue": "500",
          "keyDesc": "法定第一数量",
          "value": "500",
          "key": "qty1"
        },
        {
          "processBitMap": "0",
          "sourceList": [
            {
              "attType": "Declaration",
              "imageId": 3,
              "transformValue": "0|0|玻璃，铝合金框架 塑料底盘|无|90X90X201.5CM||",
              "originalValue": "0|0|玻璃，铝合金框架 塑料底盘|无|90X90X201.5CM||",
              "normalizedValue": "0|0|玻璃，铝合金框架 塑料底盘|无|90X90X201.5CM||",
              "processBitMap": "0",
              "axisX": 128,
              "sepValue": "0|0|玻璃，铝合金框架 塑料底盘|无|90X90X201.5CM||",
              "axisY": 1026,
              "width": 1522,
              "attTypeCode": 4,
              "height": 271
            }
          ],
          "source_image": 3,
          "originalValue": "0|0|玻璃，铝合金框架 塑料底盘|无|90X90X201.5CM||",
          "normalizedValue": "0|0|玻璃，铝合金框架 塑料底盘|无|90X90X201.5CM||",
          "keyDesc": "规格型号",
          "value": "0|0|玻璃，铝合金框架 塑料底盘|无|90X90X201.5CM||",
          "key": "gModel"
        },
        {
          "processBitMap": "0",
          "sourceList": [
            {
              "attType": "Declaration",
              "imageId": 3,
              "transformValue": "CHN",
              "originalValue": "中国",
              "normalizedValue": "中国",
              "processBitMap": "0",
              "axisX": 284,
              "sepValue": "中国",
              "axisY": 1274,
              "width": 62,
              "attTypeCode": 4,
              "height": 33
            }
          ],
          "source_image": 3,
          "originalValue": "中国",
          "normalizedValue": "CHN",
          "keyDesc": "原产国",
          "value": "CHN",
          "key": "cusOriginCountry"
        },
        {
          "processBitMap": "0",
          "sourceList": [
            {
              "attType": "Declaration",
              "imageId": 3,
              "transformValue": "POL",
              "originalValue": "波兰",
              "normalizedValue": "波兰",
              "processBitMap": "0",
              "axisX": 575,
              "sepValue": "波兰",
              "axisY": 1274,
              "width": 63,
              "attTypeCode": 4,
              "height": 33
            }
          ],
          "source_image": 3,
          "originalValue": "波兰",
          "normalizedValue": "POL",
          "keyDesc": "最终目的国",
          "value": "POL",
          "key": "destinationCountry"
        },
        {
          "processBitMap": "0",
          "sourceList": [
            {
              "attType": "Declaration",
              "imageId": 3,
              "transformValue": "33169",
              "originalValue": "萧山",
              "normalizedValue": "萧山",
              "processBitMap": "0",
              "axisX": 1072,
              "sepValue": "萧山",
              "axisY": 1274,
              "width": 63,
              "attTypeCode": 4,
              "height": 33
            }
          ],
          "source_image": 3,
          "originalValue": "萧山",
          "normalizedValue": "33169",
          "keyDesc": "境内货源地",
          "value": "33169",
          "key": "districtCode"
        }
      ]
    ],
    "operateImage": [
      {
        "imageWidth": "1786",
        "originalFileName": "HLCUNG12503DTJV3报关.pdf",
        "ocrFileUrl": "http://smartebao-production-ocr.oss-cn-shanghai.aliyuncs.com/02504/756ba0fa11b34c90b16ccb732c215094/0_HLCUNG12503DTJV3%E6%8A%A5%E5%85%B3.pdf.txt",
        "imageId": 1,
        "pdfDocPage": 0,
        "originalFileUrl": "http://smartebao-production-ocr.oss-cn-shanghai.aliyuncs.com/02504/756ba0fa11b34c90b16ccb732c215094/HLCUNG12503DTJV3%E6%8A%A5%E5%85%B3.pdf",
        "imageHeight": "2526",
        "originalImageWidth": "1786",
        "imageUrl": "https://smartebao-dub-zd-ocr.oss-cn-shanghai.aliyuncs.com/ocr/operateImage/2026-03-06/2fbdc17585366d16f1208b3300dd323c.png",
        "angle": 0,
        "originalImageHeight": "2526",
        "attTypeCode": 2,
        "imageSuffix": "png"
      },
      {
        "imageWidth": "1786",
        "originalFileName": "HLCUNG12503DTJV3报关.pdf",
        "ocrFileUrl": "http://smartebao-production-ocr.oss-cn-shanghai.aliyuncs.com/02504/756ba0fa11b34c90b16ccb732c215094/1_HLCUNG12503DTJV3%E6%8A%A5%E5%85%B3.pdf.txt",
        "imageId": 2,
        "pdfDocPage": 1,
        "originalFileUrl": "http://smartebao-production-ocr.oss-cn-shanghai.aliyuncs.com/02504/756ba0fa11b34c90b16ccb732c215094/HLCUNG12503DTJV3%E6%8A%A5%E5%85%B3.pdf",
        "imageHeight": "2526",
        "originalImageWidth": "1786",
        "imageUrl": "https://smartebao-dub-zd-ocr.oss-cn-shanghai.aliyuncs.com/ocr/operateImage/2026-03-06/06d7a5ac6001550f6fb13feceba0ddb1.png",
        "angle": 0,
        "originalImageHeight": "2526",
        "attTypeCode": 3,
        "imageSuffix": "png"
      },
      {
        "imageWidth": "1786",
        "originalFileName": "HLCUNG12503DTJV3报关.pdf",
        "ocrFileUrl": "http://smartebao-production-ocr.oss-cn-shanghai.aliyuncs.com/02504/756ba0fa11b34c90b16ccb732c215094/2_HLCUNG12503DTJV3%E6%8A%A5%E5%85%B3.pdf.txt",
        "imageId": 3,
        "pdfDocPage": 2,
        "originalFileUrl": "http://smartebao-production-ocr.oss-cn-shanghai.aliyuncs.com/02504/756ba0fa11b34c90b16ccb732c215094/HLCUNG12503DTJV3%E6%8A%A5%E5%85%B3.pdf",
        "imageHeight": "2526",
        "originalImageWidth": "1786",
        "imageUrl": "https://smartebao-dub-zd-ocr.oss-cn-shanghai.aliyuncs.com/ocr/operateImage/2026-03-06/1c20f82ddbe490a379554928e1a834d9.png",
        "angle": 0,
        "originalImageHeight": "2526",
        "attTypeCode": 4,
        "imageSuffix": "png"
      },
      {
        "imageWidth": "1786",
        "originalFileName": "HLCUNG12503DTJV3报关.pdf",
        "ocrFileUrl": "http://smartebao-production-ocr.oss-cn-shanghai.aliyuncs.com/02504/756ba0fa11b34c90b16ccb732c215094/3_HLCUNG12503DTJV3%E6%8A%A5%E5%85%B3.pdf.txt",
        "imageId": 4,
        "pdfDocPage": 3,
        "originalFileUrl": "http://smartebao-production-ocr.oss-cn-shanghai.aliyuncs.com/02504/756ba0fa11b34c90b16ccb732c215094/HLCUNG12503DTJV3%E6%8A%A5%E5%85%B3.pdf",
        "imageHeight": "2526",
        "originalImageWidth": "1786",
        "imageUrl": "https://smartebao-dub-zd-ocr.oss-cn-shanghai.aliyuncs.com/ocr/operateImage/2026-03-06/3ddc358c61c8e2cea0e83557ada66089.png",
        "angle": 0,
        "originalImageHeight": "2526",
        "attTypeCode": 1,
        "imageSuffix": "png"
      }
    ],
    "preDecContainer": []
  }
}